dwave/system/tuning/__init__.py
dwave_system_tuning-0.0.0.dev3.dist-info/DESCRIPTION.rst
dwave_system_tuning-0.0.0.dev3.dist-info/METADATA
dwave_system_tuning-0.0.0.dev3.dist-info/RECORD
dwave_system_tuning-0.0.0.dev3.dist-info/WHEEL
dwave_system_tuning-0.0.0.dev3.dist-info/metadata.json
dwave_system_tuning-0.0.0.dev3.dist-info/top_level.txt
